bbdirtree/COLORS.py
bbdirtree/__init__.py
bbdirtree/__main__.py
bbdirtree/unixvolumeinfo.py
bbdirtree/winvolumeinfo.py
bb_dirtree-0.4.1.dist-info/LICENSE
bb_dirtree-0.4.1.dist-info/METADATA
bb_dirtree-0.4.1.dist-info/WHEEL
bb_dirtree-0.4.1.dist-info/entry_points.txt
bb_dirtree-0.4.1.dist-info/RECORD
