Metadata-Version: 2.1
Name: bb-dirtree
Version: 0.4.1
Summary: Create a nice looking directory tree with options
License: MIT
Keywords: script,qt,files
Author: Erik Beebe
Author-email: beebeapps_feedback@tuta.io
Requires-Python: >=3.10,<4.0
Classifier: License :: OSI Approved :: MIT License
Classifier: Programming Language :: Python :: 3
Classifier: Programming Language :: Python :: 3.10
Classifier: Programming Language :: Python :: 3.11
Requires-Dist: bb-apputils (>=0.4.0,<0.5.0)
Requires-Dist: tabulate (>=0.8.9,<0.9.0)
